bioprinter/__init__.py
bioprinter/bioprinter.py
bioprinter/version.py
bioprinter-0.1.6.dist-info/licenses/LICENCE.txt
examples/dolly_bioprint.py
tests/test_basics.py
bioprinter-0.1.6.dist-info/METADATA
bioprinter-0.1.6.dist-info/WHEEL
bioprinter-0.1.6.dist-info/top_level.txt
bioprinter-0.1.6.dist-info/RECORD
