Metadata-Version: 2.4
Name: bioprinter
Version: 0.1.6
Summary: Print pictures with living micro-organisms!
Author: Zulko
License-Expression: MIT
Project-URL: Homepage, https://github.com/Edinburgh-Genome-Foundry/bioprinter
Keywords: bioprinter,pointillism,living,art
License-File: LICENCE.txt
Requires-Dist: numpy
Requires-Dist: Pillow
Dynamic: license-file
